AUTHORS.rst
CHANGELOG.rst
LICENSE
MANIFEST.in
README.rst
setup.cfg
setup.py
django_webix_sender/__init__.py
django_webix_sender/admin.py
django_webix_sender/apps.py
django_webix_sender/models.py
django_webix_sender/settings.py
django_webix_sender/urls.py
django_webix_sender/utils.py
django_webix_sender/views.py
django_webix_sender.egg-info/PKG-INFO
django_webix_sender.egg-info/SOURCES.txt
django_webix_sender.egg-info/dependency_links.txt
django_webix_sender.egg-info/requires.txt
django_webix_sender.egg-info/top_level.txt
django_webix_sender/locale/ca/LC_MESSAGES/django.po
django_webix_sender/locale/de/LC_MESSAGES/django.po
django_webix_sender/locale/en/LC_MESSAGES/django.po
django_webix_sender/locale/es/LC_MESSAGES/django.po
django_webix_sender/locale/fr/LC_MESSAGES/django.po
django_webix_sender/locale/it/LC_MESSAGES/django.po
django_webix_sender/migrations/0001_initial.py
django_webix_sender/migrations/0002_auto_20181109_1419.py
django_webix_sender/migrations/__init__.py
django_webix_sender/send_methods/__init__.py
django_webix_sender/send_methods/email.py
django_webix_sender/send_methods/skebby.py
django_webix_sender/templates/django_webix_sender/invoices.js
django_webix_sender/templates/django_webix_sender/list.js
django_webix_sender/templates/django_webix_sender/sender.js
django_webix_sender/templatetags/__init__.py
django_webix_sender/templatetags/field_type.py
django_webix_sender/templatetags/verbose_name.py
tests/__init__.py
tests/settings.py
tests/urls.py